manticore_cockroachdb/__init__.py
manticore_cockroachdb/async_database.py
manticore_cockroachdb/async_migration.py
manticore_cockroachdb/database.py
manticore_cockroachdb/migration.py
manticore_cockroachdb/crud/__init__.py
manticore_cockroachdb/crud/async_table.py
manticore_cockroachdb/crud/exceptions.py
manticore_cockroachdb/crud/table.py
tests/__init__.py
tests/conftest.py
tests/run_tests.py
tests/test_async_database.py
tests/test_async_migration.py
tests/test_async_table.py
tests/test_connection.py
tests/test_database.py
tests/test_migration.py
tests/test_table.py
tests/test_utils.py
manticore_cockroachdb-0.3.1.dist-info/LICENSE
manticore_cockroachdb-0.3.1.dist-info/METADATA
manticore_cockroachdb-0.3.1.dist-info/WHEEL
manticore_cockroachdb-0.3.1.dist-info/top_level.txt
manticore_cockroachdb-0.3.1.dist-info/RECORD
