Metadata-Version: 2.2
Name: manticore-cockroachdb
Version: 0.3.1
Summary: High-performance CockroachDB client library with connection pooling, migrations, transaction management, and async support
Home-page: https://manticore.technology
Author: Manticore Technologies
Author-email: Manticore Technologies <dev@manticore.technology>
License: Proprietary
Project-URL: Homepage, https://manticore.technology
Project-URL: Documentation, https://docs.manticore.technology/cockroachdb
Project-URL: Source, https://github.com/manticore-tech/manticore-cockroachdb
Keywords: cockroachdb,database,migrations,transactions,manticore,enterprise,cloud,async,asyncio
Classifier: Development Status :: 4 - Beta
Classifier: Intended Audience :: Developers
Classifier: License :: Other/Proprietary License
Classifier: Operating System :: OS Independent
Classifier: Programming Language :: Python
Classifier: Programming Language :: Python :: 3
Classifier: Programming Language :: Python :: 3.8
Classifier: Programming Language :: Python :: 3.9
Classifier: Programming Language :: Python :: 3.10
Classifier: Programming Language :: Python :: 3.11
Classifier: Topic :: Database
Classifier: Topic :: Software Development :: Libraries :: Python Modules
Classifier: Framework :: AsyncIO
Classifier: Typing :: Typed
Requires-Python: >=3.8
License-File: LICENSE
Requires-Dist: psycopg[binary]>=3.1.18
Requires-Dist: psycopg-pool>=3.2.1
Provides-Extra: dev
Requires-Dist: pytest>=8.0.0; extra == "dev"
Requires-Dist: pytest-asyncio>=0.23.5; extra == "dev"
Requires-Dist: pytest-cov>=4.1.0; extra == "dev"
Requires-Dist: black>=24.1.0; extra == "dev"
Requires-Dist: isort>=5.13.0; extra == "dev"
Requires-Dist: mypy>=1.8.0; extra == "dev"
Requires-Dist: build>=1.0.0; extra == "dev"
Requires-Dist: twine>=4.0.0; extra == "dev"
Provides-Extra: docs
Requires-Dist: mkdocs>=1.5.0; extra == "docs"
Requires-Dist: mkdocs-material>=9.5.0; extra == "docs"
Requires-Dist: mkdocstrings>=0.24.0; extra == "docs"
Requires-Dist: mkdocstrings-python>=1.7.0; extra == "docs"
Dynamic: author
Dynamic: home-page
Dynamic: requires-python
